{
    "uuid": [
        {
            "value": "0c452fa6-a1ea-4442-a644-7244ebd23019"
        }
    ],
    "langcode": [
        {
            "value": "en"
        }
    ],
    "type": [
        {
            "target_id": "page",
            "target_type": "node_type",
            "target_uuid": "86f030aa-5c45-42f9-9355-b116953c7c15"
        }
    ],
    "revision_timestamp": [
        {
            "value": "2022-06-27T15:10:05+00:00",
            "format": "Y-m-d\\TH:i:sP"
        }
    ],
    "revision_uid": [
        {
            "target_type": "user",
            "target_uuid": "dd60c32b-46de-4e9e-a31b-333e03a0c032"
        }
    ],
    "revision_log": [],
    "status": [
        {
            "value": true
        }
    ],
    "uid": [
        {
            "target_type": "user",
            "target_uuid": "dd60c32b-46de-4e9e-a31b-333e03a0c032"
        }
    ],
    "title": [
        {
            "value": "FAQs"
        }
    ],
    "created": [
        {
            "value": "2022-04-14T16:56:13+00:00",
            "format": "Y-m-d\\TH:i:sP"
        }
    ],
    "changed": [
        {
            "value": "2022-06-27T15:10:05+00:00",
            "format": "Y-m-d\\TH:i:sP"
        }
    ],
    "promote": [
        {
            "value": false
        }
    ],
    "sticky": [
        {
            "value": false
        }
    ],
    "default_langcode": [
        {
            "value": true
        }
    ],
    "revision_translation_affected": [
        {
            "value": true
        }
    ],
    "path": [
        {
            "alias": "\/faqs",
            "langcode": "en"
        }
    ],
    "body": [
        {
            "value": "<h2>General<\/h2>\r\n\r\n<h3><a href=\"#what_can_I_submit\">What can I submit to DigiNole?<\/a><\/h3>\r\n\r\n<h3><a href=\"#who_can_submit\">Who can submit to DigiNole?<\/a><\/h3>\r\n\r\n<h3><a href=\"#what_form_to_use\">What submission form should I use?<\/a><\/h3>\r\n\r\n<h3><a href=\"#university_archives\">Can I use this site to submit materials to the University Archives?<\/a><\/h3>\r\n\r\n<h3><a href=\"#data_deposit\">What materials should my data deposit include?<\/a><\/h3>\r\n\r\n<h3><a href=\"#after_submission\">How long will it take my materials to be available online after submitting?<\/a><\/h3>\r\n\r\n<h3><a href=\"#copyright\">Where can I find information about copyright and legal agreements?<\/a><\/h3>\r\n\r\n<p>&nbsp;<\/p>\r\n\r\n<p><a id=\"what_can_I_submit\"><strong>What can I submit to DigiNole?<\/strong><\/a><\/p>\r\n\r\n<p>We accept various research outputs for submission to the DigiNole repository.<\/p>\r\n\r\n<ul>\r\n\t<li>Journal articles<\/li>\r\n\t<li>Theses and dissertations<\/li>\r\n\t<li>Honors Theses<\/li>\r\n\t<li>Working papers<\/li>\r\n\t<li>Research\/technical reports<\/li>\r\n\t<li>Capstone projects<\/li>\r\n\t<li>Conference papers\/proceedings<\/li>\r\n\t<li>Conference presentations<\/li>\r\n\t<li>Posters<\/li>\r\n\t<li>Data sets<\/li>\r\n\t<li>3D models<\/li>\r\n<\/ul>\r\n\r\n<p>If what you are trying to submit is not listed here, please select \u201cOther\u201d in the submission form list or <a href=\"\/help\">contact us<\/a>.<\/p>\r\n\r\n<p>Accepted file types vary by submission form and can be found listed within the form below the file attachment section.<\/p>\r\n\r\n<p>&nbsp;<\/p>\r\n\r\n<p><a id=\"who_can_submit\"><strong>Who can submit to DigiNole?<\/strong><\/a><\/p>\r\n\r\n<p>Anyone who is a member of the FSU community with a valid FSUID can log into the submission form and upload their work to the repository. Work can also be uploaded by a non-author as long as they too have an FSUID.<\/p>\r\n\r\n<p>&nbsp;<\/p>\r\n\r\n<p><a id=\"what_form_to_use\"><strong>What submission form should I use?<\/strong><\/a><\/p>\r\n\r\n<p>Currently, there are 15 different submission forms to choose from. Each form is designed with unique fields to accurately describe the content being submitted. If there is any confusion regarding what submission form is best for you, please read the following descriptions:<\/p>\r\n\r\n<ul>\r\n\t<li>3D Object\r\n\t<ul>\r\n\t\t<li>A form intended for a file or set of files representing 3D models.<\/li>\r\n\t<\/ul>\r\n\t<\/li>\r\n\t<li>Audio\r\n\t<ul>\r\n\t\t<li>A form for those submitting a file containing audio data. A resource primarily intended to be heard. Examples include a music playback file format, an audio compact disc, and recorded speech or sounds.<\/li>\r\n\t<\/ul>\r\n\t<\/li>\r\n\t<li>Book\r\n\t<ul>\r\n\t\t<li>A form for those submitting a file containing a complete monograph, textbook, or other long-form publication. A non-serial publication that is complete in one volume or a designated finite number of volumes.<\/li>\r\n\t<\/ul>\r\n\t<\/li>\r\n\t<li>Capstone Project\r\n\t<ul>\r\n\t\t<li>A generic form for use by programs who want their student\u2019s capstone projects shared online. The Doctoral Nursing Program has its own form.<\/li>\r\n\t<\/ul>\r\n\t<\/li>\r\n\t<li>Conference\r\n\t<ul>\r\n\t\t<li>A form for those submitting a file containing information or materials presented at or associated with an academic conference. These can include papers, posters, and presentation slides.<\/li>\r\n\t<\/ul>\r\n\t<\/li>\r\n\t<li>Data Set\r\n\t<ul>\r\n\t\t<li>A form for those submitting a file or set of files containing an assembled collection of data associated with a specific scholarly\/research project or experiment.<\/li>\r\n\t<\/ul>\r\n\t<\/li>\r\n\t<li>Doctoral Nursing Program Capstone Project\r\n\t<ul>\r\n\t\t<li>A form for use by students submitting their Doctoral Nursing Program capstone project.<\/li>\r\n\t<\/ul>\r\n\t<\/li>\r\n\t<li>Editorial\r\n\t<ul>\r\n\t\t<li>A form for those submitting a brief essay expressing the opinion or position of the chief editor(s) of a (academic) journal with respect to a current political, social, cultural, or professional issue.<\/li>\r\n\t<\/ul>\r\n\t<\/li>\r\n\t<li>Honors Thesis\r\n\t<ul>\r\n\t\t<li>A form for those submitting their honors thesis.<\/li>\r\n\t<\/ul>\r\n\t<\/li>\r\n\t<li>Journal Article\r\n\t<ul>\r\n\t\t<li>A form for those submitting an article, typically the realization of a research paper reporting original research findings, published in a journal issue.<\/li>\r\n\t<\/ul>\r\n\t<\/li>\r\n\t<li>Report\r\n\t<ul>\r\n\t\t<li>A form for those submitting a report. A report is a separately published record of research findings, research still in progress, policy developments and events, or other technical findings, usually bearing a report number and sometimes a grant number assigned by the funding agency. In a more general sense, any formal account of facts or information related to a specific event or phenomenon, sometimes given at regular intervals.<\/li>\r\n\t\t<li>If you are submitting a report about the overall work of a university college, school, department, office or center, you should contact the University Archivist at lib-specialcollections@fsu.edu to see if you need to deposit a copy in the University Archives.<\/li>\r\n\t<\/ul>\r\n\t<\/li>\r\n\t<li>Review\r\n\t<ul>\r\n\t\t<li>A form for those submitting a review or critique of others' published work. For example, a book review or commentary.<\/li>\r\n\t<\/ul>\r\n\t<\/li>\r\n\t<li>Video\r\n\t<ul>\r\n\t\t<li>A form for those submitting a recording of visual images, usually in motion and possibly sound accompaniment.<\/li>\r\n\t<\/ul>\r\n\t<\/li>\r\n\t<li>Working Paper\r\n\t<ul>\r\n\t\t<li>A form for those submitting a working or discussion paper circulated publicly or among a group of peers. Certain disciplines, for example economics, issue working papers in series.<\/li>\r\n\t<\/ul>\r\n\t<\/li>\r\n\t<li>Other\r\n\t<ul>\r\n\t\t<li>This is a generic \u201ccatch-all\u201d form for a submission that doesn\u2019t fit into a pre-defined category.<\/li>\r\n\t<\/ul>\r\n\t<\/li>\r\n<\/ul>\r\n\r\n<p>Please contact <a href=\"mailto:lib-support@fsu.edu\">lib-support@fsu.edu<\/a> for submission assistance. Most definitions follow the <a href=\"https:\/\/vocabularies.coar-repositories.org\/\">COAR Repositories vocabulary<\/a>.<\/p>\r\n\r\n<p>&nbsp;<\/p>\r\n\r\n<p><a id=\"university_archives\"><strong>Can I use this site to submit materials to the University Archives?<\/strong><\/a><\/p>\r\n\r\n<p>FSU University Archives maintains a separate process for submission. Please visit the <a href=\"https:\/\/www.lib.fsu.edu\/sca\/heritage-and-university-archives\/university-records\">University Archives website<\/a> for more information.<\/p>\r\n\r\n<p>&nbsp;<\/p>\r\n\r\n<p><a id=\"data_deposit\"><strong>What materials should my data deposit include?<\/strong><\/a><\/p>\r\n\r\n<p>For those wanting to upload data sets as their research output or part of a grant funded project can find a detailed breakdown of what we want included with the data sets by reading the <a href=\"https:\/\/www.lib.fsu.edu\/data-deposit-policy\">Data Deposit Policy<\/a>.<\/p>\r\n\r\n<p>&nbsp;<\/p>\r\n\r\n<p><a id=\"after_submission\"><strong>How long will it take my materials to be available online after submitting?<\/strong><\/a><\/p>\r\n\r\n<p>The duration of time it takes to review and upload submissions can vary depending on the complexity of the files being submitted or the volume of submissions received. Submissions that are approved should expect a 24 hour to 3 day processing time before being available online. Approved Honors Theses should expect 1-2 weeks processing time after their final due date.<\/p>\r\n\r\n<p>&nbsp;<\/p>\r\n\r\n<p><a id=\"copyright\"><strong>Where can I find information about copyright and legal agreements?<\/strong><\/a><\/p>\r\n\r\n<p>The <a href=\"https:\/\/diginole.lib.fsu.edu\/copyright-and-legal-information\">Copyright and Legal Information page<\/a> consolidates information regarding content guidelines, rights, legal agreements, the notice and takedown policy, etc. When submitting work to the repository users grant FSU an non-exclusive right to preserve and reproduce the work which is explained in the <a href=\"https:\/\/diginole.lib.fsu.edu\/copyright-and-legal-information#author-agreement\">author agreement<\/a>.<\/p>\r\n",
            "format": "full_html",
            "summary": ""
        }
    ]
}